cdk_cloudformation_awscommunity_cloudfront_s3website_module/__init__.py
cdk_cloudformation_awscommunity_cloudfront_s3website_module/py.typed
cdk_cloudformation_awscommunity_cloudfront_s3website_module/_jsii/__init__.py
cdk_cloudformation_awscommunity_cloudfront_s3website_module/_jsii/awscommunity-cloudfront-s3website-module@1.16.0-alpha.7.jsii.tgz
cdk_cloudformation_awscommunity_cloudfront_s3website_module-1.16.0a7.dist-info/LICENSE
cdk_cloudformation_awscommunity_cloudfront_s3website_module-1.16.0a7.dist-info/METADATA
cdk_cloudformation_awscommunity_cloudfront_s3website_module-1.16.0a7.dist-info/WHEEL
cdk_cloudformation_awscommunity_cloudfront_s3website_module-1.16.0a7.dist-info/top_level.txt
cdk_cloudformation_awscommunity_cloudfront_s3website_module-1.16.0a7.dist-info/RECORD
